comps/__init__.py
comps/version.py
comps/cores/__init__.py
comps/cores/common/__init__.py
comps/cores/common/component.py
comps/cores/common/storage.py
comps/cores/mcp/__init__.py
comps/cores/mcp/client.py
comps/cores/mcp/config.py
comps/cores/mcp/manager.py
comps/cores/mcp/tool.py
comps/cores/mega/__init__.py
comps/cores/mega/base_service.py
comps/cores/mega/base_statistics.py
comps/cores/mega/cli.py
comps/cores/mega/config.py
comps/cores/mega/constants.py
comps/cores/mega/dag.py
comps/cores/mega/exporter.py
comps/cores/mega/http_service.py
comps/cores/mega/logger.py
comps/cores/mega/mega_service.yaml
comps/cores/mega/micro_service.py
comps/cores/mega/orchestrator.py
comps/cores/mega/orchestrator_with_yaml.py
comps/cores/mega/utils.py
comps/cores/proto/__init__.py
comps/cores/proto/api_protocol.py
comps/cores/proto/docarray.py
comps/cores/storages/__init__.py
comps/cores/storages/arangodb.py
comps/cores/storages/models.py
comps/cores/storages/mongodb.py
comps/cores/storages/redisdb.py
comps/cores/storages/stores.py
comps/cores/telemetry/__init__.py
comps/cores/telemetry/opea_telemetry.py
opea_comps-1.5.dist-info/licenses/LICENSE
opea_comps-1.5.dist-info/METADATA
opea_comps-1.5.dist-info/WHEEL
opea_comps-1.5.dist-info/entry_points.txt
opea_comps-1.5.dist-info/top_level.txt
opea_comps-1.5.dist-info/RECORD
