Metadata-Version: 2.4
Name: opea-comps
Version: 1.5
Summary: Generative AI components
Home-page: https://github.com/opea-project/GenAIComps
Author: Intel DCAI Software
Author-email: liang1.lv@intel.com, haihao.shen@intel.com, suyue.chen@intel.com
License: Apache 2.0
Keywords: GenAI
Classifier: Intended Audience :: Science/Research
Classifier: Programming Language :: Python :: 3
Classifier: Topic :: Scientific/Engineering :: Artificial Intelligence
Classifier: License :: OSI Approved :: Apache Software License
Requires-Python: >=3.8.0
License-File: LICENSE
Requires-Dist: aiofiles==24.1.0
Requires-Dist: aiohappyeyeballs==2.6.1
Requires-Dist: aiohttp==3.12.15
Requires-Dist: aiosignal==1.4.0
Requires-Dist: annotated-doc==0.0.4
Requires-Dist: annotated-types==0.7.0
Requires-Dist: anyio==4.10.0
Requires-Dist: async-timeout==5.0.1; python_full_version < "3.11.3"
Requires-Dist: attrs==25.3.0
Requires-Dist: cachetools==5.5.2
Requires-Dist: certifi==2025.8.3
Requires-Dist: cffi==2.0.0; platform_python_implementation != "PyPy"
Requires-Dist: charset-normalizer==3.4.3
Requires-Dist: click==8.2.1
Requires-Dist: colorama==0.4.6; sys_platform == "win32"
Requires-Dist: cryptography==46.0.3
Requires-Dist: dataclasses-json==0.6.7
Requires-Dist: dnspython==2.7.0
Requires-Dist: docarray==0.41.0
Requires-Dist: docx2txt==0.9
Requires-Dist: durationpy==0.10
Requires-Dist: fastapi==0.124.0
Requires-Dist: frozenlist==1.7.0
Requires-Dist: google-auth==2.40.3
Requires-Dist: googleapis-common-protos==1.70.0
Requires-Dist: greenlet==3.2.4; (python_full_version < "3.14" and platform_machine == "AMD64") or (python_full_version < "3.14" and platform_machine == "WIN32") or (python_full_version < "3.14" and platform_machine == "aarch64") or (python_full_version < "3.14" and platform_machine == "amd64") or (python_full_version < "3.14" and platform_machine == "ppc64le") or (python_full_version < "3.14" and platform_machine == "win32") or (python_full_version < "3.14" and platform_machine == "x86_64")
Requires-Dist: grpcio==1.74.0
Requires-Dist: h11==0.16.0
Requires-Dist: httpcore==1.0.9
Requires-Dist: httpx==0.28.1
Requires-Dist: httpx-sse==0.4.1
Requires-Dist: idna==3.10
Requires-Dist: importlib-metadata==8.7.0
Requires-Dist: jsonpatch==1.33
Requires-Dist: jsonpointer==3.0.0
Requires-Dist: jsonschema==4.25.1
Requires-Dist: jsonschema-specifications==2025.4.1
Requires-Dist: kubernetes==33.1.0
Requires-Dist: langchain==0.3.27
Requires-Dist: langchain-community==0.3.27
Requires-Dist: langchain-core==0.3.80
Requires-Dist: langchain-text-splitters==0.3.9
Requires-Dist: langsmith==0.4.14
Requires-Dist: markdown-it-py==4.0.0
Requires-Dist: marshmallow==3.26.1
Requires-Dist: mcp==1.23.0
Requires-Dist: mdurl==0.1.2
Requires-Dist: motor==3.7.1
Requires-Dist: multidict==6.6.4
Requires-Dist: mypy-extensions==1.1.0
Requires-Dist: numpy==2.3.2
Requires-Dist: oauthlib==3.3.1
Requires-Dist: opentelemetry-api==1.36.0
Requires-Dist: opentelemetry-exporter-otlp==1.36.0
Requires-Dist: opentelemetry-exporter-otlp-proto-common==1.36.0
Requires-Dist: opentelemetry-exporter-otlp-proto-grpc==1.36.0
Requires-Dist: opentelemetry-exporter-otlp-proto-http==1.36.0
Requires-Dist: opentelemetry-proto==1.36.0
Requires-Dist: opentelemetry-sdk==1.36.0
Requires-Dist: opentelemetry-semantic-conventions==0.57b0
Requires-Dist: orjson==3.11.2
Requires-Dist: packaging==25.0
Requires-Dist: pillow==11.3.0
Requires-Dist: prometheus-client==0.22.1
Requires-Dist: prometheus-fastapi-instrumentator==7.1.0
Requires-Dist: propcache==0.3.2
Requires-Dist: protobuf==6.32.0
Requires-Dist: pyasn1==0.6.1
Requires-Dist: pyasn1-modules==0.4.2
Requires-Dist: pycparser==2.23; implementation_name != "PyPy" and platform_python_implementation != "PyPy"
Requires-Dist: pydantic==2.11.7
Requires-Dist: pydantic-core==2.33.2
Requires-Dist: pydantic-settings==2.10.1
Requires-Dist: pygments==2.19.2
Requires-Dist: pyjwt==2.10.1
Requires-Dist: pymongo==4.14.0
Requires-Dist: pypdf==6.4.0
Requires-Dist: python-arango==8.2.2
Requires-Dist: python-arango-async==1.0.2
Requires-Dist: python-dateutil==2.9.0.post0
Requires-Dist: python-dotenv==1.1.1
Requires-Dist: python-multipart==0.0.20
Requires-Dist: pywin32==311; sys_platform == "win32"
Requires-Dist: pyyaml==6.0.2
Requires-Dist: redis==6.4.0
Requires-Dist: referencing==0.36.2
Requires-Dist: requests==2.32.5
Requires-Dist: requests-oauthlib==2.0.0
Requires-Dist: requests-toolbelt==1.0.0
Requires-Dist: rich==14.1.0
Requires-Dist: rpds-py==0.27.0
Requires-Dist: rsa==4.9.1
Requires-Dist: setuptools==80.9.0
Requires-Dist: shortuuid==1.0.13
Requires-Dist: six==1.17.0
Requires-Dist: sniffio==1.3.1
Requires-Dist: sqlalchemy==2.0.43
Requires-Dist: sse-starlette==3.0.2
Requires-Dist: starlette==0.49.1
Requires-Dist: tenacity==9.1.2
Requires-Dist: types-requests==2.32.4.20250809
Requires-Dist: typing-extensions==4.14.1
Requires-Dist: typing-inspect==0.9.0
Requires-Dist: typing-inspection==0.4.1
Requires-Dist: urllib3==2.6.0
Requires-Dist: uvicorn==0.35.0
Requires-Dist: websocket-client==1.8.0
Requires-Dist: yarl==1.20.1
Requires-Dist: zipp==3.23.0
Requires-Dist: zstandard==0.24.0
Dynamic: author
Dynamic: author-email
Dynamic: classifier
Dynamic: description
Dynamic: description-content-type
Dynamic: home-page
Dynamic: keywords
Dynamic: license
Dynamic: license-file
Dynamic: requires-dist
Dynamic: requires-python
Dynamic: summary
